{
	"class" : {
		 },
	"instance" : {
		"checkCode:on:" : "till-later 6/18/2018 17:18",
		"checkLectureMethod:" : "till-later 6/18/2018 17:19",
		"codeToEdit" : "hks 5/22/2018 11:52",
		"descriptionBoxContent" : "js 6/3/2018 15:09",
		"enableEvaluation" : "ps 6/11/2018 23:04",
		"lectureMethod" : "ps 6/26/2018 13:24",
		"lectureName" : "ps 6/26/2018 13:22",
		"passed" : "till-later 6/18/2018 17:17",
		"resetLecture" : "till-later 6/18/2018 17:12",
		"simulateWorkspace" : "js 6/16/2018 10:35",
		"solutionMethod" : "js 7/9/2018 12:06",
		"solutionNilMethod" : "js 7/9/2018 11:07" } }
