{
	"class" : {
		"instance" : "till-later 5/14/2018 18:48",
		"instance:" : "till-later 5/14/2018 18:47",
		"resetAll" : "hks 5/22/2018 13:35" },
	"instance" : {
		"adaptCodeForDisplay:" : "js 7/9/2018 11:29",
		"adaptCodeFromDisplay:" : "js 7/9/2018 11:18",
		"checkCode:on:" : "js 7/9/2018 11:19",
		"checkLectureMethod:" : "till-later 5/25/2018 12:25",
		"codeToEdit" : "js 6/27/2018 13:29",
		"crossArray:with:" : "js 7/9/2018 11:01",
		"descriptionBoxContent" : "hks 5/22/2018 11:06",
		"enableEvaluation" : "ps 6/11/2018 23:04",
		"extractMethodBody:" : "js 7/9/2018 11:25",
		"extractMethodName:" : "till-later 6/18/2018 17:04",
		"extractParameterNamesFrom:" : "js 7/9/2018 10:25",
		"failWith:" : "hks 6/11/2018 16:30",
		"feedback" : "hks 5/22/2018 11:06",
		"feedback:" : "hks 5/22/2018 11:10",
		"firstLineOfCode" : "js 6/27/2018 13:27",
		"initialize" : "hks 6/11/2018 15:53",
		"lectureMethod" : "ps 6/26/2018 12:13",
		"lectureName" : "ps 6/26/2018 12:13",
		"methodName" : "js 7/9/2018 10:59",
		"parameterNames" : "js 6/27/2018 10:52",
		"pass" : "hks 6/11/2018 16:27",
		"passed" : "hks 5/22/2018 11:07",
		"passed:" : "hks 5/22/2018 11:07",
		"performLectureMethodWith:" : "ps 7/6/2018 14:39",
		"resetLecture" : "ps 7/4/2018 01:04",
		"select:withIndex:" : "js 6/27/2018 10:36",
		"setFailed" : "hks 5/22/2018 11:07",
		"setPassed" : "ps 6/9/2018 15:03",
		"setUp:" : "hks 6/18/2018 16:23",
		"simulateWorkspace" : "js 6/16/2018 10:08",
		"solution" : "js 7/9/2018 11:14",
		"solutionMethod" : "js 7/9/2018 10:10" } }
